{
  "objectInfo" : {
    "id" : "7iyBxZnfrUXgy8ALCGhvSW",
    "name" : "VCS_ForceUndoCheckoutTest",
    "type" : "Project",
    "metadata" : {
      "modelVersion" : {
        "major" : 0,
        "minor" : 0
      },
      "repoInfo" : null,
      "contextAttributes" : [ ],
      "additionalInfo" : {
        "description" : "",
        "contentType" : "Binary",
        "documentState" : "COMPLETE"
      }
    }
  },
  "dataFileExtension" : "json",
  "updateTime" : "2023-12-14T07:03:00.797Z",
  "objectRefs" : [ ]
}